proximal_gradient/__init__.py
proximal_gradient/proximalGradient.py
proximal_gradient-0.1.0.dist-info/LICENSE.txt
proximal_gradient-0.1.0.dist-info/METADATA
proximal_gradient-0.1.0.dist-info/WHEEL
proximal_gradient-0.1.0.dist-info/top_level.txt
proximal_gradient-0.1.0.dist-info/RECORD
