Metadata-Version: 2.1
Name: proximal-gradient
Version: 0.1.0
Summary: Proximal Gradient Methods for Pytorch
Home-page: https://github.com/KentonMurray/ProxGradPytorch
Author: Kenton Murray
Author-email: kmurray4@nd.edu
License: LICENSE.txt
Platform: UNKNOWN
Requires-Dist: torch (>=0.4.0)
